skeleton_hand-0.2.0.dist-info/licenses/LICENSE
skhand/HandInput.py
skhand/__init__.py
skhand/HandData/Gestrue.py
skhand/HandData/Models.py
skhand/HandData/OneHand.py
skhand/HandData/_global.py
skhand/HandData/models/if_out_model.onnx
skhand/HandData/models/if_touch_model.onnx
skhand/HandData/models/im_close_model.onnx
skhand/HandData/models/mf_out_model.onnx
skhand/HandData/models/mf_touch_model.onnx
skhand/HandData/models/mr_close_model.onnx
skhand/HandData/models/pk_out_model.onnx
skhand/HandData/models/pk_touch_model.onnx
skhand/HandData/models/rf_out_model.onnx
skhand/HandData/models/rf_touch_model.onnx
skhand/HandData/models/rp_close_model.onnx
skhand/HandData/models/tb_out_model.onnx
skhand/HandData/models/ti_close_model.onnx
skhand/HandDetector/HandsMatchers.py
skhand/HandDetector/MediaPipeHandDetector.py
skhand/HandDetector/VisualHandDetector.py
skhand/HandInputSchemes/FingerSwipeScheme.py
skhand/HandInputSchemes/FingertipButtonScheme.py
skhand/HandInputSchemes/HandInputScheme.py
skhand/HandInputSchemes/ThumbJoystickScheme.py
skhand/HandUtils/Camera.py
skhand/HandUtils/Drawing.py
skhand/HandUtils/Filter.py
skeleton_hand-0.2.0.dist-info/METADATA
skeleton_hand-0.2.0.dist-info/WHEEL
skeleton_hand-0.2.0.dist-info/top_level.txt
skeleton_hand-0.2.0.dist-info/RECORD
