Metadata-Version: 2.4
Name: skeleton-hand
Version: 0.2.0
Summary: A comprehensive hand tracking and gesture recognition framework
Author-email: Expien1 <lzhao2077@qq.com>
License-Expression: Apache-2.0
Project-URL: Homepage, https://github.com/Expien1/skeleton-hand
Project-URL: Issues, https://github.com/Expien1/skeleton-hand/issues
Keywords: hand tracking,gesture recognition,computer vision,machine learning,hand keypoints
Classifier: Programming Language :: Python :: 3.12
Classifier: Operating System :: OS Independent
Classifier: Intended Audience :: Developers
Classifier: Topic :: Software Development :: Libraries :: Python Modules
Classifier: Topic :: Scientific/Engineering :: Image Recognition
Requires-Python: >=3.12
License-File: LICENSE
Requires-Dist: numpy>=2.0.2
Requires-Dist: pandas>=2.2.3
Requires-Dist: onnxruntime>=1.20.1
Requires-Dist: mediapipe>=0.10.14
Dynamic: license-file
